slackoff/__init__.py
slackoff/excel/__init__.py
slackoff/excel/merge.py
slackoff/toj/__init__.py
slackoff/toj/reconciliation.py
slackoff/toj/reconciliation_exper_processor.py
slackoff/toj/reconciliation_packing.py
slackoff/toj/reconciliation_rule.py
slackoff/toj/reconciliation_source.py
slackoff/toj/reconciliation_to_excel.py
slackoff/toj/reconcilization_merge.py
slackoff/toj/utils.py
slack_off_mj-0.1.5.dist-info/LICENSE
slack_off_mj-0.1.5.dist-info/METADATA
slack_off_mj-0.1.5.dist-info/WHEEL
slack_off_mj-0.1.5.dist-info/top_level.txt
slack_off_mj-0.1.5.dist-info/RECORD
