Metadata-Version: 2.1
Name: slack-off-mj
Version: 0.1.5
Summary: 可以把多个数据源，转换为JSON。通过自定义合并规则，对多个JSON源进行合并，最后定义写入规则可以写到excel，目前应用在一些对账场景
Author: 蒋经雄
Author-email: 723137901@qq.com
Requires-Python: >=3.6
License-File: LICENSE
